Metadata-Version: 2.1
Name: pyrtfolio
Version: 0.4
Summary: pyrtfolio - Python package to generate stock portfolios
Home-page: https://pyrtfolio.readthedocs.io/
Author: Alvaro Bartolome
Author-email: alvarobartt@usal.es
License: GNU General Public License v3 (GPLv3)
Download-URL: https://github.com/alvarobartt/pyrtfolio/archive/0.4.tar.gz
Project-URL: Bug Reports, https://github.com/alvarobartt/pyrtfolio/issues
Project-URL: Source, https://github.com/alvarobartt/pyrtfolio
Project-URL: Documentation, https://pyrtfolio.readthedocs.io/
Keywords: investing,investing-api,investpy,financial-data,stocks,portfolio
Platform: UNKNOWN
Classifier: Development Status :: 4 - Beta
Classifier: Programming Language :: Python :: 3 :: Only
Classifier: Programming Language :: Python :: 3.5
Classifier: Programming Language :: Python :: 3.6
Classifier: Programming Language :: Python :: 3.7
Classifier: Programming Language :: Python :: 3.8
Classifier: License :: OSI Approved :: GNU General Public License v3 (GPLv3)
Classifier: Intended Audience :: Developers
Classifier: Topic :: Office/Business :: Financial
Classifier: Topic :: Office/Business :: Financial :: Investment
Classifier: Topic :: Scientific/Engineering :: Information Analysis
Requires-Python: >=3
